neware_utils/__init__.py
neware_utils/protocols/__init__.py
neware_utils/protocols/protocol.py
neware_utils/protocols/step_modes.py
neware_utils-1.0.1.dist-info/licenses/LICENSE
neware_utils-1.0.1.dist-info/METADATA
neware_utils-1.0.1.dist-info/WHEEL
neware_utils-1.0.1.dist-info/top_level.txt
neware_utils-1.0.1.dist-info/RECORD
